gumnut/__init__.py
gumnut/_base_client.py
gumnut/_client.py
gumnut/_compat.py
gumnut/_constants.py
gumnut/_exceptions.py
gumnut/_files.py
gumnut/_models.py
gumnut/_qs.py
gumnut/_resource.py
gumnut/_response.py
gumnut/_streaming.py
gumnut/_types.py
gumnut/_version.py
gumnut/pagination.py
gumnut/py.typed
gumnut/_utils/__init__.py
gumnut/_utils/_compat.py
gumnut/_utils/_datetime_parse.py
gumnut/_utils/_json.py
gumnut/_utils/_logs.py
gumnut/_utils/_proxy.py
gumnut/_utils/_reflection.py
gumnut/_utils/_resources_proxy.py
gumnut/_utils/_streams.py
gumnut/_utils/_sync.py
gumnut/_utils/_transform.py
gumnut/_utils/_typing.py
gumnut/_utils/_utils.py
gumnut/lib/.keep
gumnut/resources/__init__.py
gumnut/resources/api_keys.py
gumnut/resources/assets.py
gumnut/resources/events.py
gumnut/resources/faces.py
gumnut/resources/libraries.py
gumnut/resources/oauth.py
gumnut/resources/people.py
gumnut/resources/search.py
gumnut/resources/users.py
gumnut/resources/albums/__init__.py
gumnut/resources/albums/albums.py
gumnut/resources/albums/assets.py
gumnut/types/__init__.py
gumnut/types/album_asset_event_payload.py
gumnut/types/album_asset_response.py
gumnut/types/album_create_params.py
gumnut/types/album_event_payload.py
gumnut/types/album_list_params.py
gumnut/types/album_response.py
gumnut/types/album_update_params.py
gumnut/types/api_key_create_params.py
gumnut/types/api_key_create_response.py
gumnut/types/api_key_list_response.py
gumnut/types/api_key_response.py
gumnut/types/api_key_update_params.py
gumnut/types/asset_check_existence_params.py
gumnut/types/asset_create_params.py
gumnut/types/asset_download_thumbnail_params.py
gumnut/types/asset_event_payload.py
gumnut/types/asset_existence_response.py
gumnut/types/asset_list_params.py
gumnut/types/asset_lite_response.py
gumnut/types/asset_response.py
gumnut/types/auth_url_response.py
gumnut/types/event_get_params.py
gumnut/types/events_response.py
gumnut/types/exchange_response.py
gumnut/types/exif_event_payload.py
gumnut_sdk-0.39.0.dist-info/METADATA
gumnut_sdk-0.39.0.dist-info/WHEEL
gumnut_sdk-0.39.0.dist-info/licenses/LICENSE
gumnut_sdk-0.39.0.dist-info/RECORD
